Alpha_Mind-0.3.1.data/scripts/alphamind
alphamind/__init__.py
alphamind/api.py
alphamind/utilities.py
alphamind/analysis/__init__.py
alphamind/analysis/calculators.py
alphamind/analysis/crosssetctions.py
alphamind/analysis/factoranalysis.py
alphamind/analysis/perfanalysis.py
alphamind/analysis/quantileanalysis.py
alphamind/analysis/riskanalysis.py
alphamind/benchmarks/__init__.py
alphamind/benchmarks/benchmarks.py
alphamind/benchmarks/data/__init__.py
alphamind/benchmarks/data/neutralize.py
alphamind/benchmarks/data/standardize.py
alphamind/benchmarks/data/winsorize.py
alphamind/benchmarks/portfolio/__init__.py
alphamind/benchmarks/portfolio/linearbuild.py
alphamind/benchmarks/portfolio/longshortbuild.py
alphamind/benchmarks/portfolio/percentbuild.py
alphamind/benchmarks/portfolio/rankbuild.py
alphamind/benchmarks/settlement/__init__.py
alphamind/benchmarks/settlement/simplesettle.py
alphamind/bin/__init__.py
alphamind/bin/alphamind
alphamind/bin/cli.py
alphamind/data/__init__.py
alphamind/data/neutralize.py
alphamind/data/processing.py
alphamind/data/quantile.py
alphamind/data/rank.py
alphamind/data/standardize.py
alphamind/data/transformer.py
alphamind/data/winsorize.py
alphamind/data/dbmodel/__init__.py
alphamind/data/dbmodel/models/__init__.py
alphamind/data/dbmodel/models/mysql.py
alphamind/data/dbmodel/models/postgres.py
alphamind/data/engines/__init__.py
alphamind/data/engines/industries.py
alphamind/data/engines/universe.py
alphamind/data/engines/utilities.py
alphamind/data/engines/sqlengine/__init__.py
alphamind/data/engines/sqlengine/mysql.py
alphamind/data/engines/sqlengine/postgres.py
alphamind/exceptions/__init__.py
alphamind/exceptions/exceptions.py
alphamind/execution/__init__.py
alphamind/execution/baseexecutor.py
alphamind/execution/naiveexecutor.py
alphamind/execution/pipeline.py
alphamind/execution/targetvolexecutor.py
alphamind/execution/thresholdexecutor.py
alphamind/formula/__init__.py
alphamind/formula/utilities.py
alphamind/model/__init__.py
Alpha_Mind-0.3.1.dist-info/LICENSE.txt
Alpha_Mind-0.3.1.dist-info/METADATA
Alpha_Mind-0.3.1.dist-info/WHEEL
Alpha_Mind-0.3.1.dist-info/top_level.txt
Alpha_Mind-0.3.1.dist-info/RECORD
