Metadata-Version: 2.1
Name: Alpha-Mind
Version: 0.3.1
Summary: UNKNOWN
Home-page: UNKNOWN
Author: wegamekinglc
Author-email: UNKNOWN
License: MIT
Platform: UNKNOWN
Requires-Dist: arrow
Requires-Dist: cython
Requires-Dist: cvxpy
Requires-Dist: cvxopt
Requires-Dist: deprecated
Requires-Dist: ecos
Requires-Dist: finance-python
Requires-Dist: jupyter
Requires-Dist: jupyterlab
Requires-Dist: matplotlib
Requires-Dist: mysqlclient
Requires-Dist: numba
Requires-Dist: numpy
Requires-Dist: pandas
Requires-Dist: portfolio-optimizer
Requires-Dist: psycopg2-binary
Requires-Dist: scikit-learn
Requires-Dist: scipy
Requires-Dist: simpleutils
Requires-Dist: sqlalchemy
Requires-Dist: statsmodels
Requires-Dist: xgboost
Requires-Dist: xlsxwriter
